<?xml version="1.0" encoding="utf-8"?>
<!DOCTYPE hibernate-mapping PUBLIC "-//Hibernate/Hibernate Mapping DTD 3.0//EN"
"http://hibernate.sourceforge.net/hibernate-mapping-3.0.dtd">
<!-- 
    Mapping file autogenerated by MyEclipse Persistence Tools
-->
<hibernate-mapping>
    <class name="com.soarsky.octopus.mapping.TUserClient" table="T_USER_CLIENT" schema="ZHUANKER">
        <id name="id" type="java.lang.Long">
            <column name="ID" />
            <generator class="sequence">
                <param name="sequence">SEQ_PRI_USER_CLIENT</param>
            </generator>
        </id>
        <many-to-one name="tArea" class="com.soarsky.octopus.mapping.TArea">
            <column name="AREA_ID" >
            </column>
        </many-to-one>
        <property name="parentId" type="java.lang.Long">
            <column name="PARENT_ID" >
            </column>
        </property>
        <property name="userName" type="java.lang.String">
            <column name="USER_NAME" />
        </property>
        <property name="password" type="java.lang.String">
            <column name="PASSWORD" />
        </property>
        <property name="nickName" type="java.lang.String">
            <column name="NICK_NAME" />
        </property>
        <property name="phone" type="java.lang.String">
            <column name="PHONE" />
        </property>
        <property name="constellation" type="java.lang.String">
            <column name="CONSTELLATION" />
        </property>
        <property name="midcode" type="java.lang.String">
            <column name="MIDCODE" >
            </column>
        </property>
        <property name="email" type="java.lang.String">
            <column name="EMAIL" />
        </property>
        <property name="registerType" type="java.lang.Integer">
            <column name="REGISTER_TYPE" >
            </column>
        </property>
        <property name="sex" type="java.lang.Integer">
            <column name="SEX"  />
        </property>
        <property name="shengxiao" type="java.lang.Integer">
            <column name="SHENGXIAO" />
        </property>
        <property name="birthday" type="java.util.Date">
            <column name="BIRTHDAY"  />
        </property>
        <property name="iscompelete" type="java.lang.Boolean">
            <column name="ISCOMPELETE"  />
        </property>
        <property name="token" type="java.lang.String">
            <column name="TOKEN" />
        </property>
        <property name="registerDate" type="java.util.Date">
            <column name="REGISTER_DATE" />
        </property>
        
        <property name="leveCode" type="java.lang.String">
            <column name="LEVECODE" />
        </property>
        
        <property name="apkUrl" type="java.lang.String">
            <column name="APKURL" />
        </property>
        <property name="finishedTaskNum" type="java.lang.Integer">
            <column name="FINISHED_TASK_NUM" />
        </property>
        
        <property name="age" type="java.lang.Integer">
            <column name="AGE" />
        </property>
        
        <property name="inviteCode" type="java.lang.Long">
            <column name="INVITECODE"></column>
        </property>
        
        <many-to-one name="tProfessio" column="profession" unique="true" lazy="false" fetch="join"></many-to-one>
        <many-to-one name="channel" class="com.soarsky.octopus.mapping.TChannel" fetch="join" lazy="false">
            <column name="CHANNELID" />
        </many-to-one> 

        <set name="tUserGoldCounts" >
            <key>
                <column name="USER_ID"  />
            </key>
            <one-to-many class="com.soarsky.octopus.mapping.TUserGoldCount" />
        </set>
        <set name="tSystemFlows" >
            <key>
                <column name="USE_ID"  />
            </key>
            <one-to-many class="com.soarsky.octopus.mapping.TSystemFlow" />
        </set>
        <set name="tInstalledApks" >
            <key>
                <column name="USER_ID" />
            </key>
            <one-to-many class="com.soarsky.octopus.mapping.TInstalledApk" />
        </set>
        <set name="tExchangeLogs" >
            <key>
                <column name="USER_ID" />
            </key>
            <one-to-many class="com.soarsky.octopus.mapping.TExchangeLog" />
        </set>
        <set name="tDownloadInstallLogs" >
            <key>
                <column name="USER_ID"  />
            </key>
            <one-to-many class="com.soarsky.octopus.mapping.TDownloadInstallLog" />
        </set>
        <set name="tUserTasks" >
            <key>
                <column name="USER_ID"  />
            </key>
            <one-to-many class="com.soarsky.octopus.mapping.TUserTask" />
        </set>
        <set name="tUserPositions" >
            <key>
                <column name="USER_ID"  />
            </key>
            <one-to-many class="com.soarsky.octopus.mapping.TUserPosition" />
        </set>
        <set name="tUserHobbieses">
            <key>
                <column name="USER_ID" />
            </key>
            <one-to-many class="com.soarsky.octopus.mapping.TUserHobbies" />
        </set>
        <set name="tSuggections" >
            <key>
                <column name="USER_ID" />
            </key>
            <one-to-many class="com.soarsky.octopus.mapping.TSuggection" />
        </set>
        <set name="tGoldChanges" >
            <key>
                <column name="USER_ID" />
            </key>
            <one-to-many class="com.soarsky.octopus.mapping.TGoldChange" />
        </set>
        <set name="tClientLoginLogs" >
            <key>
                <column name="USER_ID"  />
            </key>
            <one-to-many class="com.soarsky.octopus.mapping.TClientLoginLog" />
        </set>
    </class>
</hibernate-mapping>
